neurolog/__init__.py
neurolog/util/__init__.py
neurolog/util/generic.py
neurolog-0.0.1.dist-info/LICENSE
neurolog-0.0.1.dist-info/METADATA
neurolog-0.0.1.dist-info/WHEEL
neurolog-0.0.1.dist-info/top_level.txt
neurolog-0.0.1.dist-info/RECORD
