Metadata-Version: 2.1
Name: neurolog
Version: 0.0.1
Summary: Neurolog (pre-alpha)
Author-email: Sam Griesemer <samgriesemer+git@gmail.com>
Project-URL: Homepage, https://doc.olog.io/neurolog
Project-URL: Documentation, https://doc.olog.io/neurolog
Project-URL: Repository, https://git.olog.io/olog/neurolog
Project-URL: Issues, https://git.olog.io/olog/neurolog/issues
Keywords: database,disk
Classifier: Programming Language :: Python :: 3.12
Classifier: License :: OSI Approved :: MIT License
Classifier: Operating System :: OS Independent
Classifier: Development Status :: 1 - Planning
Classifier: Intended Audience :: Developers
Requires-Python: >=3.12
License-File: LICENSE
Requires-Dist: co3
Requires-Dist: execlib
Requires-Dist: sqlalchemy
Provides-Extra: tests
Requires-Dist: pytest; extra == "tests"
Provides-Extra: docs
Requires-Dist: sphinx; extra == "docs"
Requires-Dist: sphinx-togglebutton; extra == "docs"
Requires-Dist: sphinx-autodoc-typehints; extra == "docs"
Requires-Dist: furo; extra == "docs"
Requires-Dist: myst-parser; extra == "docs"
